tests/__init__.py
tests/test_model_factory.py
tte_models/ModelFactory.py
tte_models/__init__.py
tte_models/my_model.py
tte_models/ratio.py
tte_utils/__init__.py
tte_utils/dataset.py
tte_utils/loader.py
tte_utils/metrics.py
tte_utils/split.py
tte_utils/styles.py
tte-1.1.0.dist-info/LICENSE.txt
tte-1.1.0.dist-info/METADATA
tte-1.1.0.dist-info/WHEEL
tte-1.1.0.dist-info/top_level.txt
tte-1.1.0.dist-info/RECORD
