Metadata-Version: 2.1
Name: tte
Version: 1.1.0
Summary: A simple Python package
Home-page: https://github.com/ExtraFlash/TimeToEventPackage
Author: Or Shkuri
Author-email: orshkuri2000@gmail.com
Classifier: Programming Language :: Python :: 3
Classifier: License :: OSI Approved :: MIT License
Classifier: Operating System :: OS Independent
Requires-Python: >=3.6
License-File: LICENSE.txt
